{
	"criteria": {
		"channel_lightning_on_mooshroom_at_spawn": {
			"trigger": "minecraft:channeled_lightning",
			"conditions": {
				"victims": [
					[
						{
							"condition": "minecraft:all_of",
							"terms": [
								{
									"condition": "minecraft:entity_properties",
									"entity": "this",
									"predicate": {
										"type": "minecraft:mooshroom"
									}
								},
								{
									"condition": "minecraft:reference",
									"name": "pandamium:in_spawn"
								}
							]
						}
					]
				]
			}
		}
	},
	"rewards": {
		"function": "pandamium:detect/channel_lightning_on_mooshroom_at_spawn/main"
	}
}
