{
	"display": {
		"icon": {
			"id": "minecraft:player_head",
			"components": {
				"minecraft:profile": {
					"id": [
						0,
						0,
						0,
						0
					],
					"properties": [
						{
							"name": "textures",
							"value": "eyJ0ZXh0dXJlcyI6eyJTS0lOIjp7InVybCI6Imh0dHA6Ly90ZXh0dXJlcy5taW5lY3JhZnQubmV0L3RleHR1cmUvNGZjNmI2YWIwMmQ3MmY0YjhlNjgxNjEwOTNlNjY5Yzc4NzEyOGViZmZiNWRmNzQxY2Y5ZWVmODMzMjBlNWNmZSJ9fX0="
						}
					]
				}
			}
		},
		"title": "Which Came First?",
		"description": [
			"Craft a Mini Dragon Egg"
		],
		"frame": "challenge",
		"show_toast": true,
		"hidden": true
	},
	"parent": "pandamium:pandamium/mini_blocks/obtain_heavy_core_mini_block",
	"criteria": {
		"obtain_dragon_egg_mini_block": {
			"trigger": "minecraft:recipe_crafted",
			"conditions": {
				"recipe_id": "pandamium:mini_blocks/dragon_egg/dragon_egg"
			}
		}
	},
	"requirements": [
		[
			"obtain_dragon_egg_mini_block"
		]
	]
}
